memos_webhook/__init__.py
memos_webhook/app.py
memos_webhook/constants/__init__.py
memos_webhook/dependencies/config.py
memos_webhook/dependencies/memos_cli.py
memos_webhook/dependencies/plugin_manager.py
memos_webhook/langchains/__init__.py
memos_webhook/langchains/chains.py
memos_webhook/langchains/zhipu.py
memos_webhook/plugins/__init__.py
memos_webhook/plugins/base_plugin.py
memos_webhook/plugins/base_plugin_test.py
memos_webhook/plugins/you_get_plugin.py
memos_webhook/plugins/you_get_plugin_test.py
memos_webhook/plugins/zhipu_plugin.py
memos_webhook/proto_gen/__init__.py
memos_webhook/proto_gen/google/__init__.py
memos_webhook/proto_gen/google/api/__init__.py
memos_webhook/proto_gen/memos/__init__.py
memos_webhook/proto_gen/memos/api/__init__.py
memos_webhook/proto_gen/memos/api/v1/__init__.py
memos_webhook/utils/__init__.py
memos_webhook/utils/logger.py
memos_webhook/utils/config_decorators/__init__.py
memos_webhook/utils/config_decorators/common.py
memos_webhook/utils/config_decorators/from_args.py
memos_webhook/utils/config_decorators/from_args_test.py
memos_webhook/utils/config_decorators/from_env.py
memos_webhook/utils/config_decorators/from_env_test.py
memos_webhook/utils/config_decorators/from_unmarshal.py
memos_webhook/utils/config_decorators/from_unmarshal_test.py
memos_webhook/webhook/__init__.py
memos_webhook/webhook/type_transform.py
memos_webhook/webhook/types/__init__.py
memos_webhook/webhook/types/common.py
memos_webhook/webhook/types/google_protobuf.py
memos_webhook/webhook/types/markdown_service.py
memos_webhook/webhook/types/memo_relation_service.py
memos_webhook/webhook/types/memo_service.py
memos_webhook/webhook/types/reaction.py
memos_webhook/webhook/types/resource_service.py
memos_webhook/webhook/types/webhook_payload.py
memos_webhook-0.6.0.dist-info/LICENSE
memos_webhook-0.6.0.dist-info/METADATA
memos_webhook-0.6.0.dist-info/WHEEL
memos_webhook-0.6.0.dist-info/top_level.txt
memos_webhook-0.6.0.dist-info/RECORD
