Metadata-Version: 2.1
Name: memos_webhook
Version: 0.6.0
Summary: A webhook server for memos
Author: RyoJerryYu
License: MIT License
Project-URL: Homepage, https://github.com/RyoJerryYu/memos-webhook-py
Project-URL: Issues, https://github.com/RyoJerryYu/memos-webhook-py/issues
Classifier: Programming Language :: Python :: 3
Classifier: License :: OSI Approved :: MIT License
Requires-Python: >=3.12
License-File: LICENSE
Requires-Dist: aiofiles ==23.2.1
Requires-Dist: aiohttp ==3.9.5
Requires-Dist: aiosignal ==1.3.1
Requires-Dist: annotated-types ==0.7.0
Requires-Dist: anyio ==4.4.0
Requires-Dist: attrs ==23.2.0
Requires-Dist: betterproto ==2.0.0b6
Requires-Dist: black ==24.4.2
Requires-Dist: build ==1.2.1
Requires-Dist: cachetools ==5.3.3
Requires-Dist: certifi ==2024.6.2
Requires-Dist: charset-normalizer ==3.3.2
Requires-Dist: click ==8.1.7
Requires-Dist: dacite ==1.8.1
Requires-Dist: dnspython ==2.6.1
Requires-Dist: docutils ==0.21.2
Requires-Dist: email-validator ==2.1.1
Requires-Dist: fastapi ==0.111.0
Requires-Dist: fastapi-cli ==0.0.4
Requires-Dist: frozenlist ==1.4.1
Requires-Dist: grpclib ==0.4.8rc1
Requires-Dist: h11 ==0.14.0
Requires-Dist: h2 ==4.1.0
Requires-Dist: hpack ==4.0.0
Requires-Dist: httpcore ==1.0.5
Requires-Dist: httptools ==0.6.1
Requires-Dist: httpx ==0.27.0
Requires-Dist: hyperframe ==6.0.1
Requires-Dist: idna ==3.7
Requires-Dist: importlib-metadata ==7.1.0
Requires-Dist: isort ==5.13.2
Requires-Dist: jaraco.classes ==3.4.0
Requires-Dist: jaraco.context ==5.3.0
Requires-Dist: jaraco.functools ==4.0.1
Requires-Dist: Jinja2 ==3.1.4
Requires-Dist: jsonpatch ==1.33
Requires-Dist: jsonpointer ==3.0.0
Requires-Dist: keyring ==25.2.1
Requires-Dist: langchain ==0.2.4
Requires-Dist: langchain-core ==0.2.6
Requires-Dist: langchain-text-splitters ==0.2.1
Requires-Dist: langsmith ==0.1.77
Requires-Dist: markdown-it-py ==3.0.0
Requires-Dist: MarkupSafe ==2.1.5
Requires-Dist: mdurl ==0.1.2
Requires-Dist: more-itertools ==10.2.0
Requires-Dist: multidict ==6.0.5
Requires-Dist: mypy-extensions ==1.0.0
Requires-Dist: nh3 ==0.2.17
Requires-Dist: numpy ==1.26.4
Requires-Dist: orjson ==3.10.3
Requires-Dist: packaging ==24.0
Requires-Dist: pathspec ==0.12.1
Requires-Dist: pkginfo ==1.11.0
Requires-Dist: platformdirs ==4.2.2
Requires-Dist: pydantic ==2.7.1
Requires-Dist: pydantic-core ==2.18.2
Requires-Dist: Pygments ==2.18.0
Requires-Dist: PyJWT ==2.8.0
Requires-Dist: pyproject-hooks ==1.1.0
Requires-Dist: python-dateutil ==2.9.0.post0
Requires-Dist: python-dotenv ==1.0.1
Requires-Dist: python-multipart ==0.0.9
Requires-Dist: PyYAML ==6.0.1
Requires-Dist: readme-renderer ==43.0
Requires-Dist: requests ==2.32.3
Requires-Dist: requests-toolbelt ==1.0.0
Requires-Dist: rfc3986 ==2.0.0
Requires-Dist: rich ==13.7.1
Requires-Dist: setuptools ==70.0.0
Requires-Dist: shellingham ==1.5.4
Requires-Dist: six ==1.16.0
Requires-Dist: sniffio ==1.3.1
Requires-Dist: SQLAlchemy ==2.0.30
Requires-Dist: starlette ==0.37.2
Requires-Dist: tenacity ==8.3.0
Requires-Dist: twine ==5.1.0
Requires-Dist: typer ==0.12.3
Requires-Dist: types-aiofiles ==23.2.0.20240403
Requires-Dist: types-PyYAML ==6.0.12.20240311
Requires-Dist: typing-extensions ==4.12.1
Requires-Dist: ujson ==5.10.0
Requires-Dist: urllib3 ==2.2.1
Requires-Dist: uvicorn ==0.30.0
Requires-Dist: uvloop ==0.19.0
Requires-Dist: watchfiles ==0.22.0
Requires-Dist: websockets ==12.0
Requires-Dist: yarl ==1.9.4
Requires-Dist: you-get ==0.4.1700
Requires-Dist: zhipuai ==2.1.0.20240521
Requires-Dist: zipp ==3.19.2
Provides-Extra: dev
Requires-Dist: betterproto[compiler] ; extra == 'dev'
